{
  "squad": [
    {
      "player_id": 469,
      "full_name": "Nick Pope",
      "team_name": "Newcastle",
      "team_id": 15,
      "element_type": 1,
      "now_cost_millions": 5.0,
      "expected_points": 6.899888933051541,
      "start_probability": 0.9132388986953178,
      "confidence_score": 93.4,
      "confidence_level": "High",
      "expected_points_lower_80": 6.507,
      "expected_points_upper_80": 7.292,
      "starting": 1,
      "bench": 0,
      "captain": 0,
      "next_fixture": "BOU (A)"
    },
    {
      "player_id": 575,
      "full_name": "Micky van de Ven",
      "team_name": "Spurs",
      "team_id": 18,
      "element_type": 2,
      "now_cost_millions": 4.4,
      "expected_points": 6.32081156904947,
      "start_probability": 0.907881458472579,
      "confidence_score": 93.5,
      "confidence_level": "High",
      "expected_points_lower_80": 5.96,
      "expected_points_upper_80": 6.682,
      "starting": 1,
      "bench": 0,
      "captain": 0,
      "next_fixture": "BHA (A)"
    },
    {
      "player_id": 7,
      "full_name": "Riccardo Calafiori",
      "team_name": "Arsenal",
      "team_id": 1,
      "element_type": 2,
      "now_cost_millions": 5.6,
      "expected_points": 6.291645367647939,
      "start_probability": 0.8721945298316709,
      "confidence_score": 89.1,
      "confidence_level": "High",
      "expected_points_lower_80": 5.557,
      "expected_points_upper_80": 7.026,
      "starting": 1,
      "bench": 0,
      "captain": 0,
      "next_fixture": "MCI (H)"
    },
    {
      "player_id": 569,
      "full_name": "Cristian Romero",
      "team_name": "Spurs",
      "team_id": 18,
      "element_type": 2,
      "now_cost_millions": 5.0,
      "expected_points": 6.167147719240392,
      "start_probability": 0.894746819222165,
      "confidence_score": 65.5,
      "confidence_level": "Medium",
      "expected_points_lower_80": 5.013,
      "expected_points_upper_80": 7.322,
      "starting": 1,
      "bench": 0,
      "captain": 0,
      "next_fixture": "BHA (A)"
    },
    {
      "player_id": 8,
      "full_name": "Jurri\u00ebn Timber",
      "team_name": "Arsenal",
      "team_id": 1,
      "element_type": 2,
      "now_cost_millions": 6.0,
      "expected_points": 6.124885381931566,
      "start_probability": 0.7806640723289742,
      "confidence_score": 69.6,
      "confidence_level": "Medium",
      "expected_points_lower_80": 5.163,
      "expected_points_upper_80": 7.086,
      "starting": 1,
      "bench": 0,
      "captain": 0,
      "next_fixture": "MCI (H)"
    },
    {
      "player_id": 291,
      "full_name": "James Tarkowski",
      "team_name": "Everton",
      "team_id": 9,
      "element_type": 2,
      "now_cost_millions": 5.8,
      "expected_points": 5.810366660908097,
      "start_probability": 0.9393011278243707,
      "confidence_score": 95.8,
      "confidence_level": "High",
      "expected_points_lower_80": 5.594,
      "expected_points_upper_80": 6.027,
      "starting": 1,
      "bench": 0,
      "captain": 0,
      "next_fixture": "LIV (A)"
    },
    {
      "player_id": 82,
      "full_name": "Antoine Semenyo",
      "team_name": "Man City",
      "team_id": 13,
      "element_type": 3,
      "now_cost_millions": 8.0,
      "expected_points": 6.835735981005469,
      "start_probability": 0.9653570913170071,
      "confidence_score": 93.9,
      "confidence_level": "High",
      "expected_points_lower_80": 6.373,
      "expected_points_upper_80": 7.299,
      "starting": 1,
      "bench": 0,
      "captain": 0,
      "next_fixture": "ARS (A)"
    },
    {
      "player_id": 26,
      "full_name": "Mart\u00edn Zubimendi Ib\u00e1\u00f1ez",
      "team_name": "Arsenal",
      "team_id": 1,
      "element_type": 3,
      "now_cost_millions": 4.9,
      "expected_points": 6.274927140463434,
      "start_probability": 0.8500328938249861,
      "confidence_score": 89.0,
      "confidence_level": "High",
      "expected_points_lower_80": 5.589,
      "expected_points_upper_80": 6.961,
      "starting": 1,
      "bench": 0,
      "captain": 0,
      "next_fixture": "MCI (H)"
    },
    {
      "player_id": 205,
      "full_name": "Josh Cullen",
      "team_name": "Burnley",
      "team_id": 3,
      "element_type": 3,
      "now_cost_millions": 4.9,
      "expected_points": 5.830187002837903,
      "start_probability": 0.9682529554825752,
      "confidence_score": 72.3,
      "confidence_level": "Medium",
      "expected_points_lower_80": 5.178,
      "expected_points_upper_80": 6.482,
      "starting": 1,
      "bench": 0,
      "captain": 0,
      "next_fixture": "NFO (H)"
    },
    {
      "player_id": 430,
      "full_name": "Erling Haaland",
      "team_name": "Man City",
      "team_id": 13,
      "element_type": 4,
      "now_cost_millions": 14.7,
      "expected_points": 9.398742864024928,
      "start_probability": 0.9437102143582198,
      "confidence_score": 84.1,
      "confidence_level": "High",
      "expected_points_lower_80": 7.261,
      "expected_points_upper_80": 11.537,
      "starting": 1,
      "bench": 0,
      "captain": 1,
      "next_fixture": "ARS (A)"
    },
    {
      "player_id": 249,
      "full_name": "Jo\u00e3o Pedro Junqueira de Jesus",
      "team_name": "Chelsea",
      "team_id": 7,
      "element_type": 4,
      "now_cost_millions": 7.4,
      "expected_points": 7.186954954281065,
      "start_probability": 0.8922987364772579,
      "confidence_score": 90.5,
      "confidence_level": "High",
      "expected_points_lower_80": 6.538,
      "expected_points_upper_80": 7.836,
      "starting": 1,
      "bench": 0,
      "captain": 0,
      "next_fixture": "MUN (A)"
    }
  ],
  "bench": [
    {
      "player_id": 241,
      "full_name": "Mois\u00e9s Caicedo Corozo",
      "team_name": "Chelsea",
      "team_id": 7,
      "element_type": 3,
      "now_cost_millions": 5.7,
      "expected_points": 5.496002745718432,
      "start_probability": 0.9070041668790273,
      "confidence_score": 94.7,
      "confidence_level": "High",
      "expected_points_lower_80": 5.251,
      "expected_points_upper_80": 5.741,
      "starting": 0,
      "bench": 1,
      "captain": 0,
      "bench_order": 1,
      "next_fixture": "MUN (A)"
    },
    {
      "player_id": 612,
      "full_name": "Lucas Tolentino Coelho de Lima",
      "team_name": "West Ham",
      "team_id": 19,
      "element_type": 3,
      "now_cost_millions": 5.9,
      "expected_points": 5.412225872379654,
      "start_probability": 0.9552904259587045,
      "confidence_score": 72.2,
      "confidence_level": "Medium",
      "expected_points_lower_80": 4.801,
      "expected_points_upper_80": 6.023,
      "starting": 0,
      "bench": 1,
      "captain": 0,
      "bench_order": 2,
      "next_fixture": "CRY (H)"
    },
    {
      "player_id": 283,
      "full_name": "Jean-Philippe Mateta",
      "team_name": "Crystal Palace",
      "team_id": 8,
      "element_type": 4,
      "now_cost_millions": 7.6,
      "expected_points": 4.934175577619431,
      "start_probability": 0.9036387288274799,
      "confidence_score": 94.6,
      "confidence_level": "High",
      "expected_points_lower_80": 4.693,
      "expected_points_upper_80": 5.176,
      "starting": 0,
      "bench": 1,
      "captain": 0,
      "bench_order": 3,
      "next_fixture": "WHU (A)"
    },
    {
      "player_id": 565,
      "full_name": "Guglielmo Vicario",
      "team_name": "Spurs",
      "team_id": 18,
      "element_type": 1,
      "now_cost_millions": 4.7,
      "expected_points": 6.594390478381948,
      "start_probability": 0.938813969359326,
      "confidence_score": 88.9,
      "confidence_level": "High",
      "expected_points_lower_80": 5.598,
      "expected_points_upper_80": 7.591,
      "starting": 0,
      "bench": 1,
      "captain": 0,
      "bench_order": 4,
      "next_fixture": "BHA (A)"
    }
  ],
  "total_cost": 95.60000000000001,
  "starting_cost": 71.7,
  "bench_cost": 23.900000000000002,
  "expected_points_without_captain": 73.1412935744418,
  "total_expected_points_with_captain": 82.54003643846673,
  "bench_expected_points": 22.436794674099467,
  "captain": "Erling Haaland",
  "formation": {
    "GK": 1,
    "DEF": 5,
    "MID": 3,
    "FWD": 2
  },
  "formation_name": "5-3-2"
}