{
  "squad": [
    {
      "player_id": 101,
      "full_name": "Caoimh\u00edn Kelleher",
      "team_name": "Brentford",
      "team_id": 5,
      "element_type": 1,
      "now_cost_millions": 4.8,
      "expected_points": 4.7121452358985,
      "start_probability": 0.9632019567224077,
      "confidence_score": 91.4,
      "confidence_level": "High",
      "expected_points_lower_80": 4.021,
      "expected_points_upper_80": 5.403,
      "starting": 1,
      "bench": 0,
      "captain": 0,
      "next_fixture": "CRY (H)"
    },
    {
      "player_id": 5,
      "full_name": "Gabriel dos Santos Magalh\u00e3es",
      "team_name": "Arsenal",
      "team_id": 1,
      "element_type": 2,
      "now_cost_millions": 7.2,
      "expected_points": 6.032814890468413,
      "start_probability": 0.9332353149347573,
      "confidence_score": 97.7,
      "confidence_level": "High",
      "expected_points_lower_80": 5.969,
      "expected_points_upper_80": 6.097,
      "starting": 1,
      "bench": 0,
      "captain": 0,
      "next_fixture": "BUR (H)"
    },
    {
      "player_id": 77,
      "full_name": "James Hill",
      "team_name": "Bournemouth",
      "team_id": 4,
      "element_type": 2,
      "now_cost_millions": 4.2,
      "expected_points": 5.507464357908777,
      "start_probability": 0.9396461656175359,
      "confidence_score": 70.4,
      "confidence_level": "Medium",
      "expected_points_lower_80": 4.779,
      "expected_points_upper_80": 6.236,
      "starting": 1,
      "bench": 0,
      "captain": 0,
      "next_fixture": "MCI (H)"
    },
    {
      "player_id": 344,
      "full_name": "Jaka Bijol",
      "team_name": "Leeds",
      "team_id": 11,
      "element_type": 2,
      "now_cost_millions": 3.9,
      "expected_points": 5.383297494704393,
      "start_probability": 0.9021715620250561,
      "confidence_score": 88.2,
      "confidence_level": "High",
      "expected_points_lower_80": 4.457,
      "expected_points_upper_80": 6.31,
      "starting": 1,
      "bench": 0,
      "captain": 0,
      "next_fixture": "BHA (H)"
    },
    {
      "player_id": 74,
      "full_name": "Adrien Truffert",
      "team_name": "Bournemouth",
      "team_id": 4,
      "element_type": 2,
      "now_cost_millions": 4.7,
      "expected_points": 5.348638624476588,
      "start_probability": 0.9567418571624386,
      "confidence_score": 68.0,
      "confidence_level": "Medium",
      "expected_points_lower_80": 4.37,
      "expected_points_upper_80": 6.327,
      "starting": 1,
      "bench": 0,
      "captain": 0,
      "next_fixture": "MCI (H)"
    },
    {
      "player_id": 449,
      "full_name": "Bruno Borges Fernandes",
      "team_name": "Man Utd",
      "team_id": 14,
      "element_type": 3,
      "now_cost_millions": 10.4,
      "expected_points": 6.059288051482766,
      "start_probability": 0.9395800495833697,
      "confidence_score": 95.5,
      "confidence_level": "High",
      "expected_points_lower_80": 5.811,
      "expected_points_upper_80": 6.308,
      "starting": 1,
      "bench": 0,
      "captain": 1,
      "next_fixture": "NFO (H)"
    },
    {
      "player_id": 457,
      "full_name": "Carlos Henrique Casimiro",
      "team_name": "Man Utd",
      "team_id": 14,
      "element_type": 3,
      "now_cost_millions": 5.8,
      "expected_points": 5.738152805388746,
      "start_probability": 0.9436584089569686,
      "confidence_score": 95.0,
      "confidence_level": "High",
      "expected_points_lower_80": 5.44,
      "expected_points_upper_80": 6.036,
      "starting": 1,
      "bench": 0,
      "captain": 0,
      "next_fixture": "NFO (H)"
    },
    {
      "player_id": 387,
      "full_name": "Dominik Szoboszlai",
      "team_name": "Liverpool",
      "team_id": 12,
      "element_type": 3,
      "now_cost_millions": 7.0,
      "expected_points": 5.643328457138565,
      "start_probability": 0.9387595126496182,
      "confidence_score": 89.1,
      "confidence_level": "High",
      "expected_points_lower_80": 4.701,
      "expected_points_upper_80": 6.586,
      "starting": 1,
      "bench": 0,
      "captain": 0,
      "next_fixture": "AVL (A)"
    },
    {
      "player_id": 200,
      "full_name": "Jaidon Anthony",
      "team_name": "Burnley",
      "team_id": 3,
      "element_type": 3,
      "now_cost_millions": 5.0,
      "expected_points": 5.642925821669524,
      "start_probability": 0.9123950482085926,
      "confidence_score": 93.7,
      "confidence_level": "High",
      "expected_points_lower_80": 5.303,
      "expected_points_upper_80": 5.983,
      "starting": 1,
      "bench": 0,
      "captain": 0,
      "next_fixture": "ARS (A)"
    },
    {
      "player_id": 83,
      "full_name": "Dango Ouattara",
      "team_name": "Brentford",
      "team_id": 5,
      "element_type": 3,
      "now_cost_millions": 5.8,
      "expected_points": 5.596733304257388,
      "start_probability": 0.8087692237845084,
      "confidence_score": 89.5,
      "confidence_level": "High",
      "expected_points_lower_80": 5.091,
      "expected_points_upper_80": 6.102,
      "starting": 1,
      "bench": 0,
      "captain": 0,
      "next_fixture": "CRY (H)"
    },
    {
      "player_id": 136,
      "full_name": "Igor Thiago Nascimento Rodrigues",
      "team_name": "Brentford",
      "team_id": 5,
      "element_type": 4,
      "now_cost_millions": 7.4,
      "expected_points": 6.038423392217824,
      "start_probability": 0.9608603197162122,
      "confidence_score": 97.2,
      "confidence_level": "High",
      "expected_points_lower_80": 5.892,
      "expected_points_upper_80": 6.185,
      "starting": 1,
      "bench": 0,
      "captain": 0,
      "next_fixture": "CRY (H)"
    }
  ],
  "bench": [
    {
      "player_id": 224,
      "full_name": "Marc Cucurella Saseta",
      "team_name": "Chelsea",
      "team_id": 7,
      "element_type": 2,
      "now_cost_millions": 6.1,
      "expected_points": 5.024473375854404,
      "start_probability": 0.9053310020479153,
      "confidence_score": 92.6,
      "confidence_level": "High",
      "expected_points_lower_80": 4.604,
      "expected_points_upper_80": 5.445,
      "starting": 0,
      "bench": 1,
      "captain": 0,
      "bench_order": 1,
      "next_fixture": "TOT (H)"
    },
    {
      "player_id": 691,
      "full_name": "Dominic Calvert-Lewin",
      "team_name": "Leeds",
      "team_id": 11,
      "element_type": 4,
      "now_cost_millions": 5.8,
      "expected_points": 4.772429206940176,
      "start_probability": 0.8893531288557357,
      "confidence_score": 93.3,
      "confidence_level": "High",
      "expected_points_lower_80": 4.459,
      "expected_points_upper_80": 5.086,
      "starting": 0,
      "bench": 1,
      "captain": 0,
      "bench_order": 2,
      "next_fixture": "BHA (H)"
    },
    {
      "player_id": 64,
      "full_name": "Ollie Watkins",
      "team_name": "Aston Villa",
      "team_id": 2,
      "element_type": 4,
      "now_cost_millions": 8.8,
      "expected_points": 4.709423970349356,
      "start_probability": 0.6006474520192531,
      "confidence_score": 80.1,
      "confidence_level": "High",
      "expected_points_lower_80": 3.779,
      "expected_points_upper_80": 5.64,
      "starting": 0,
      "bench": 1,
      "captain": 0,
      "bench_order": 3,
      "next_fixture": "LIV (H)"
    },
    {
      "player_id": 341,
      "full_name": "Karl Darlow",
      "team_name": "Leeds",
      "team_id": 11,
      "element_type": 1,
      "now_cost_millions": 4.0,
      "expected_points": 4.4514568071454566,
      "start_probability": 0.9754271764028173,
      "confidence_score": 73.3,
      "confidence_level": "Medium",
      "expected_points_lower_80": 3.958,
      "expected_points_upper_80": 4.945,
      "starting": 0,
      "bench": 1,
      "captain": 0,
      "bench_order": 4,
      "next_fixture": "BHA (H)"
    }
  ],
  "total_cost": 90.9,
  "starting_cost": 66.2,
  "bench_cost": 24.7,
  "expected_points_without_captain": 61.703212435611476,
  "total_expected_points_with_captain": 67.76250048709424,
  "bench_expected_points": 18.95778336028939,
  "captain": "Bruno Borges Fernandes",
  "formation": {
    "GK": 1,
    "DEF": 4,
    "MID": 5,
    "FWD": 1
  },
  "formation_name": "4-5-1"
}