{
  "squad": [
    {
      "player_id": 314,
      "full_name": "Bernd Leno",
      "team_name": "Fulham",
      "team_id": 10,
      "element_type": 1,
      "now_cost_millions": 4.9,
      "expected_points": 3.9782692176132435,
      "start_probability": 0.9724998588314837,
      "confidence_score": 69.0,
      "confidence_level": "Medium",
      "expected_points_lower_80": 3.168,
      "expected_points_upper_80": 4.789,
      "starting": 1,
      "bench": 0,
      "captain": 0,
      "next_fixture": "WOL (A)"
    },
    {
      "player_id": 6,
      "full_name": "William Saliba",
      "team_name": "Arsenal",
      "team_id": 1,
      "element_type": 2,
      "now_cost_millions": 6.2,
      "expected_points": 5.287563219324044,
      "start_probability": 0.8658827577251186,
      "confidence_score": 91.8,
      "confidence_level": "High",
      "expected_points_lower_80": 4.879,
      "expected_points_upper_80": 5.696,
      "starting": 1,
      "bench": 0,
      "captain": 0,
      "next_fixture": "BUR (H)"
    },
    {
      "player_id": 291,
      "full_name": "James Tarkowski",
      "team_name": "Everton",
      "team_id": 9,
      "element_type": 2,
      "now_cost_millions": 5.7,
      "expected_points": 4.98795497924719,
      "start_probability": 0.9291722334889563,
      "confidence_score": 95.7,
      "confidence_level": "High",
      "expected_points_lower_80": 4.79,
      "expected_points_upper_80": 5.186,
      "starting": 1,
      "bench": 0,
      "captain": 0,
      "next_fixture": "SUN (H)"
    },
    {
      "player_id": 5,
      "full_name": "Gabriel dos Santos Magalh\u00e3es",
      "team_name": "Arsenal",
      "team_id": 1,
      "element_type": 2,
      "now_cost_millions": 7.3,
      "expected_points": 4.822062365753503,
      "start_probability": 0.9381405219287916,
      "confidence_score": 98.0,
      "confidence_level": "High",
      "expected_points_lower_80": 4.758,
      "expected_points_upper_80": 4.886,
      "starting": 1,
      "bench": 0,
      "captain": 0,
      "next_fixture": "BUR (H)"
    },
    {
      "player_id": 807,
      "full_name": "Rayan Vitor Simpl\u00edcio Rocha",
      "team_name": "Bournemouth",
      "team_id": 4,
      "element_type": 3,
      "now_cost_millions": 5.4,
      "expected_points": 5.71327911853054,
      "start_probability": 0.8638466506331903,
      "confidence_score": 63.3,
      "confidence_level": "Medium",
      "expected_points_lower_80": 4.426,
      "expected_points_upper_80": 7.001,
      "starting": 1,
      "bench": 0,
      "captain": 1,
      "next_fixture": "MCI (H)"
    },
    {
      "player_id": 450,
      "full_name": "Matheus Santos Carneiro da Cunha",
      "team_name": "Man Utd",
      "team_id": 14,
      "element_type": 3,
      "now_cost_millions": 8.1,
      "expected_points": 5.099540486098783,
      "start_probability": 0.814071132860968,
      "confidence_score": 91.0,
      "confidence_level": "High",
      "expected_points_lower_80": 4.732,
      "expected_points_upper_80": 5.467,
      "starting": 1,
      "bench": 0,
      "captain": 0,
      "next_fixture": "NFO (H)"
    },
    {
      "player_id": 163,
      "full_name": "Jack Hinshelwood",
      "team_name": "Brighton",
      "team_id": 6,
      "element_type": 3,
      "now_cost_millions": 5.1,
      "expected_points": 4.371929310631764,
      "start_probability": 0.8904033941217459,
      "confidence_score": 94.1,
      "confidence_level": "High",
      "expected_points_lower_80": 4.127,
      "expected_points_upper_80": 4.617,
      "starting": 1,
      "bench": 0,
      "captain": 0,
      "next_fixture": "LEE (A)"
    },
    {
      "player_id": 200,
      "full_name": "Jaidon Anthony",
      "team_name": "Burnley",
      "team_id": 3,
      "element_type": 3,
      "now_cost_millions": 5.0,
      "expected_points": 4.167355738804594,
      "start_probability": 0.9029235043770834,
      "confidence_score": 95.4,
      "confidence_level": "High",
      "expected_points_lower_80": 4.005,
      "expected_points_upper_80": 4.33,
      "starting": 1,
      "bench": 0,
      "captain": 0,
      "next_fixture": "ARS (A)"
    },
    {
      "player_id": 20,
      "full_name": "Leandro Trossard",
      "team_name": "Arsenal",
      "team_id": 1,
      "element_type": 3,
      "now_cost_millions": 6.5,
      "expected_points": 4.089472754757905,
      "start_probability": 0.7038687298580923,
      "confidence_score": 81.1,
      "confidence_level": "High",
      "expected_points_lower_80": 2.936,
      "expected_points_upper_80": 5.243,
      "starting": 1,
      "bench": 0,
      "captain": 0,
      "next_fixture": "BUR (H)"
    },
    {
      "player_id": 526,
      "full_name": "Igor Jesus Maciel da Cruz",
      "team_name": "Nott'm Forest",
      "team_id": 16,
      "element_type": 4,
      "now_cost_millions": 5.9,
      "expected_points": 4.746848560762282,
      "start_probability": 0.7987538028199725,
      "confidence_score": 87.1,
      "confidence_level": "High",
      "expected_points_lower_80": 4.044,
      "expected_points_upper_80": 5.45,
      "starting": 1,
      "bench": 0,
      "captain": 0,
      "next_fixture": "MUN (A)"
    },
    {
      "player_id": 64,
      "full_name": "Ollie Watkins",
      "team_name": "Aston Villa",
      "team_id": 2,
      "element_type": 4,
      "now_cost_millions": 8.7,
      "expected_points": 3.4603608220416135,
      "start_probability": 0.8614711922398939,
      "confidence_score": 95.5,
      "confidence_level": "High",
      "expected_points_lower_80": 3.382,
      "expected_points_upper_80": 3.539,
      "starting": 1,
      "bench": 0,
      "captain": 0,
      "next_fixture": "LIV (H)"
    }
  ],
  "bench": [
    {
      "player_id": 148,
      "full_name": "Ferdi Kad\u0131o\u011flu",
      "team_name": "Brighton",
      "team_id": 6,
      "element_type": 2,
      "now_cost_millions": 4.4,
      "expected_points": 3.4250476528573994,
      "start_probability": 0.9451669665944425,
      "confidence_score": 73.1,
      "confidence_level": "Medium",
      "expected_points_lower_80": 3.036,
      "expected_points_upper_80": 3.814,
      "starting": 0,
      "bench": 1,
      "captain": 0,
      "bench_order": 1,
      "next_fixture": "LEE (A)"
    },
    {
      "player_id": 256,
      "full_name": "Daniel Mu\u00f1oz Mej\u00eda",
      "team_name": "Crystal Palace",
      "team_id": 8,
      "element_type": 2,
      "now_cost_millions": 5.9,
      "expected_points": 3.3884732551405703,
      "start_probability": 0.8967421499670511,
      "confidence_score": 88.5,
      "confidence_level": "High",
      "expected_points_lower_80": 2.586,
      "expected_points_upper_80": 4.191,
      "starting": 0,
      "bench": 1,
      "captain": 0,
      "bench_order": 2,
      "next_fixture": "BRE (A)"
    },
    {
      "player_id": 527,
      "full_name": "Taiwo Awoniyi",
      "team_name": "Nott'm Forest",
      "team_id": 16,
      "element_type": 4,
      "now_cost_millions": 5.2,
      "expected_points": 3.3765950365038906,
      "start_probability": 0.6591768658684174,
      "confidence_score": 80.7,
      "confidence_level": "High",
      "expected_points_lower_80": 2.377,
      "expected_points_upper_80": 4.376,
      "starting": 0,
      "bench": 1,
      "captain": 0,
      "bench_order": 3,
      "next_fixture": "MUN (A)"
    },
    {
      "player_id": 502,
      "full_name": "Matz Sels",
      "team_name": "Nott'm Forest",
      "team_id": 16,
      "element_type": 1,
      "now_cost_millions": 4.6,
      "expected_points": 3.4456100339156914,
      "start_probability": 0.9136304578946526,
      "confidence_score": 94.8,
      "confidence_level": "High",
      "expected_points_lower_80": 3.222,
      "expected_points_upper_80": 3.669,
      "starting": 0,
      "bench": 1,
      "captain": 0,
      "bench_order": 4,
      "next_fixture": "MUN (A)"
    }
  ],
  "total_cost": 88.9,
  "starting_cost": 68.8,
  "bench_cost": 20.1,
  "expected_points_without_captain": 50.72463657356546,
  "total_expected_points_with_captain": 56.437915692096,
  "bench_expected_points": 13.635725978417552,
  "captain": "Rayan Vitor Simpl\u00edcio Rocha",
  "formation": {
    "GK": 1,
    "DEF": 3,
    "MID": 5,
    "FWD": 2
  },
  "formation_name": "3-5-2"
}